e2fyi/__init__.py
e2fyi/utils/__init__.py
e2fyi/utils/aws/__init__.py
e2fyi/utils/aws/compat.py
e2fyi/utils/aws/s3.py
e2fyi/utils/aws/s3_resource.py
e2fyi/utils/aws/s3_resource_test.py
e2fyi/utils/aws/s3_stream.py
e2fyi/utils/aws/s3_stream_test.py
e2fyi/utils/aws/s3_test.py
e2fyi/utils/core/__init__.py
e2fyi/utils/core/maybe.py
e2fyi/utils/core/maybe_test.py
e2fyi/utils/core/results.py
e2fyi_utils-0.3.0rc1.dist-info/LICENSE
e2fyi_utils-0.3.0rc1.dist-info/WHEEL
e2fyi_utils-0.3.0rc1.dist-info/METADATA
e2fyi_utils-0.3.0rc1.dist-info/RECORD
