Metadata-Version: 2.1
Name: e2fyi-utils
Version: 0.3.0rc1
Summary: General utils for interacting with aws resources.
License: Apache-2.0
Author: eterna2
Author-email: eterna2@hotmail.com
Requires-Python: >=3.6.1,<4
Classifier: License :: OSI Approved :: Apache Software License
Classifier: Programming Language :: Python :: 3
Classifier: Programming Language :: Python :: 3.7
Classifier: Programming Language :: Python :: 3.8
Classifier: Programming Language :: Python :: 3.9
Provides-Extra: all
Provides-Extra: pandas
Requires-Dist: boto3 (>=1.9)
Requires-Dist: joblib
Requires-Dist: pandas; extra == "pandas" or extra == "all"
Requires-Dist: pydantic (>=0.30)
Requires-Dist: python-dateutil (>=2.1,<2.8.1)
Requires-Dist: python-magic (>=0.4.0,<0.5.0); sys_platform == "linux"
Requires-Dist: python-magic-bin (>=0.4.0,<0.5.0); sys_platform == "darwin" or sys_platform == "windows"
Requires-Dist: toml (>=0.10.1,<0.11.0)
Requires-Dist: typing-extensions
